soweak/__init__.py
soweak/analyzer.py
soweak/cli.py
soweak/py.typed
soweak/risk_scorer.py
soweak/detectors/__init__.py
soweak/detectors/additional_detectors.py
soweak/detectors/base.py
soweak/detectors/data_poisoning.py
soweak/detectors/prompt_injection.py
soweak/detectors/sensitive_info.py
soweak/utils/__init__.py
soweak-2.0.1.dist-info/licenses/LICENSE
soweak-2.0.1.dist-info/METADATA
soweak-2.0.1.dist-info/WHEEL
soweak-2.0.1.dist-info/entry_points.txt
soweak-2.0.1.dist-info/top_level.txt
soweak-2.0.1.dist-info/RECORD
