Metadata-Version: 2.4
Name: soweak
Version: 2.0.1
Summary: LLM Security & Prompt Injection Detection Library - OWASP Top 10 for LLM Applications 2025 vulnerability scanner for AI/ML pipelines, LangChain, OpenAI, and Google ADK integrations
Author-email: Soubhik Ghosh <99ghoshsoubhik@gmail.com>
Maintainer-email: Soubhik Ghosh <99ghoshsoubhik@gmail.com>
License: Apache-2.0
Project-URL: Homepage, https://github.com/SoubhikGhosh/soweak
Project-URL: Documentation, https://github.com/SoubhikGhosh/soweak#readme
Project-URL: Repository, https://github.com/SoubhikGhosh/soweak
Project-URL: Issues, https://github.com/SoubhikGhosh/soweak/issues
Project-URL: Changelog, https://github.com/SoubhikGhosh/soweak/blob/main/CHANGELOG.md
Project-URL: Bug Tracker, https://github.com/SoubhikGhosh/soweak/issues
Project-URL: Source Code, https://github.com/SoubhikGhosh/soweak
Keywords: llm-security,prompt-injection,prompt-injection-detection,ai-security,ml-security,vulnerability-detection,security-scanner,owasp,owasp-top-10,owasp-llm,llm-vulnerabilities,security-audit,langchain,langchain-security,openai,openai-security,google-adk,google-generative-ai,gemini,chatgpt,gpt-4,claude,anthropic,huggingface,genai,generative-ai,llm,large-language-model,nlp,nlp-security,chatbot-security,conversational-ai,jailbreak-detection,jailbreak-prevention,prompt-hacking,adversarial-attac
Classifier: Development Status :: 4 - Beta
Classifier: Intended Audience :: Developers
Classifier: Intended Audience :: Information Technology
Classifier: Intended Audience :: Science/Research
Classifier: License :: OSI Approved :: Apache Software License
Classifier: Operating System :: OS Independent
Classifier: Programming Language :: Python :: 3
Classifier: Programming Language :: Python :: 3.8
Classifier: Programming Language :: Python :: 3.9
Classifier: Programming Language :: Python :: 3.10
Classifier: Programming Language :: Python :: 3.11
Classifier: Programming Language :: Python :: 3.12
Classifier: Programming Language :: Python :: 3.13
Classifier: Topic :: Security
Classifier: Topic :: Scientific/Engineering :: Artificial Intelligence
Classifier: Topic :: Software Development :: Libraries :: Python Modules
Classifier: Topic :: Software Development :: Quality Assurance
Classifier: Topic :: Text Processing :: Filters
Classifier: Typing :: Typed
Classifier: Natural Language :: English
Classifier: Environment :: Console
Classifier: Framework :: Pytest
Requires-Python: >=3.8
License-File: LICENSE
Provides-Extra: dev
Requires-Dist: pytest>=7.0.0; extra == "dev"
Requires-Dist: pytest-cov>=4.0.0; extra == "dev"
Requires-Dist: black>=23.0.0; extra == "dev"
Requires-Dist: isort>=5.12.0; extra == "dev"
Requires-Dist: mypy>=1.0.0; extra == "dev"
Requires-Dist: flake8>=6.0.0; extra == "dev"
Requires-Dist: pre-commit>=3.0.0; extra == "dev"
Provides-Extra: docs
Requires-Dist: mkdocs>=1.5.0; extra == "docs"
Requires-Dist: mkdocs-material>=9.0.0; extra == "docs"
Requires-Dist: mkdocstrings[python]>=0.24.0; extra == "docs"
Provides-Extra: langchain
Requires-Dist: langchain>=0.1.0; extra == "langchain"
Requires-Dist: langchain-core>=0.1.0; extra == "langchain"
Provides-Extra: openai
Requires-Dist: openai>=1.0.0; extra == "openai"
Provides-Extra: google
Requires-Dist: google-generativeai>=0.3.0; extra == "google"
Requires-Dist: google-adk>=0.1.0; extra == "google"
Provides-Extra: all
Requires-Dist: langchain>=0.1.0; extra == "all"
Requires-Dist: langchain-core>=0.1.0; extra == "all"
Requires-Dist: openai>=1.0.0; extra == "all"
Requires-Dist: google-generativeai>=0.3.0; extra == "all"
Dynamic: license-file
